pixeldrain.py
Pixeldrain-1.1.2.dist-info/LICENSE
Pixeldrain-1.1.2.dist-info/METADATA
Pixeldrain-1.1.2.dist-info/WHEEL
Pixeldrain-1.1.2.dist-info/top_level.txt
Pixeldrain-1.1.2.dist-info/RECORD
