Metadata-Version: 2.1
Name: Pixeldrain
Version: 1.1.2
Summary: Pixeldrain API
Author: Fayas Noushad
License: MIT
Project-URL: Tracker, https://github.com/FayasNoushad/Pixeldrain/issues
Project-URL: Source, https://github.com/FayasNoushad/Pixeldrain
Classifier: Intended Audience :: Developers
Classifier: Natural Language :: English
Classifier: Programming Language :: Python
Classifier: License :: OSI Approved :: MIT License
Classifier: Operating System :: OS Independent
Requires-Python: >=3.6
License-File: LICENSE
